SR700_Artisan_Profile_Builder/__init__.py
SR700_Artisan_Profile_Builder-1.1.dist-info/METADATA
SR700_Artisan_Profile_Builder-1.1.dist-info/WHEEL
SR700_Artisan_Profile_Builder-1.1.dist-info/entry_points.txt
SR700_Artisan_Profile_Builder-1.1.dist-info/top_level.txt
SR700_Artisan_Profile_Builder-1.1.dist-info/RECORD
