Metadata-Version: 2.1
Name: SR700-Artisan-Profile-Builder
Version: 1.1
Summary: Create artisan profiles using the alarms and the modified version of the freshroastsr700 library for phidget
Home-page: https://github.com/lucapinello/create_artisan_alarms_phidget
Author: Luca Pinello
Author-email: UNKNOWN
License: GPLv3
Platform: UNKNOWN
Requires-Dist: scipy
Requires-Dist: numpy
Requires-Dist: matplotlib
Requires-Dist: PySide2
Requires-Dist: intervaltree
